{
    "_comment": "For right (backward) wall, inner corner depth 880, outer corner distance 660, far side extension 200",
    "weld_length": 900.0,
    "safe_height": 30.0,
    "welding_angle_wrt_y": [-101, 30, 15.0],
    "actions": [
        [-15.0, 0.0, 25,    4.0, 3, 7.0, 5, 4.0],
        [-15.0, -5.0, 0,    4.0, 3, 7.0, 5, 4.0],
        [-7.0, -10.0, 10,   4.0, 3, 6.0, 5, 4.0],
        [-7.0, -15.0, 0,    4.0, 3, 6.0, 5, 4.0],
        [2.0, 0.0, 0,       5.0, 3, 5.0, 5, 5.0],
        [2.0, -5.0, 0,      5.0, 3, 5.0, 5, 5.0],
        [2.0, -9.0, 0,      5.0, 3, 5.0, 5, 5.0],
        [2.0, -14.0, 0,     5.0, 3, 5.0, 5, 5.0],
        [2.0, -20.0, 0,     5.0, 3, 5.0, 5, 5.0],
        [2.0, -25.0, 0,     5.0, 3, 5.0, 5, 5.0]
    ]
}